{
    "homevisit": [
        {
            "districts": [
                {
                    "data": [
                        {
                            "count": 5647,
                            "title1": "Lactating Mother",
                            "iconImg": "../images/NewDashboard/home_visit_preg_women_img.png",
                            "title": "Pregnant Women &"
                        },
                        {
                            "count": 13008,
                            "title1": "(0 - 2 Years)",
                            "iconImg": "../images/NewDashboard/home_visit_child_img.png",
                            "title": "Children"
                        }
                    ],
                    "district_id": 535
                },
                {
                    "data": [
                        {
                            "count": 1505,
                            "title1": "Lactating Mother",
                            "iconImg": "../images/NewDashboard/home_visit_preg_women_img.png",
                            "title": "Pregnant Women &"
                        },
                        {
                            "count": 4672,
                            "title1": "(0 - 2 Years)",
                            "iconImg": "../images/NewDashboard/home_visit_child_img.png",
                            "title": "Children"
                        }
                    ],
                    "district_id": 536
                },
                {
                    "data": [
                        {
                            "count": 16383,
                            "title1": "Lactating Mother",
                            "iconImg": "../images/NewDashboard/home_visit_preg_women_img.png",
                            "title": "Pregnant Women &"
                        },
                        {
                            "count": 40175,
                            "title1": "(0 - 2 Years)",
                            "iconImg": "../images/NewDashboard/home_visit_child_img.png",
                            "title": "Children"
                        }
                    ],
                    "district_id": 537
                },
                {
                    "data": [
                        {
                            "count": 6195,
                            "title1": "Lactating Mother",
                            "iconImg": "../images/NewDashboard/home_visit_preg_women_img.png",
                            "title": "Pregnant Women &"
                        },
                        {
                            "count": 18465,
                            "title1": "(0 - 2 Years)",
                            "iconImg": "../images/NewDashboard/home_visit_child_img.png",
                            "title": "Children"
                        }
                    ],
                    "district_id": 538
                },
                {
                    "data": [
                        {
                            "count": 769,
                            "title1": "Lactating Mother",
                            "iconImg": "../images/NewDashboard/home_visit_preg_women_img.png",
                            "title": "Pregnant Women &"
                        },
                        {
                            "count": 6233,
                            "title1": "(0 - 2 Years)",
                            "iconImg": "../images/NewDashboard/home_visit_child_img.png",
                            "title": "Children"
                        }
                    ],
                    "district_id": 539
                },
                {
                    "data": [
                        {
                            "count": 3950,
                            "title1": "Lactating Mother",
                            "iconImg": "../images/NewDashboard/home_visit_preg_women_img.png",
                            "title": "Pregnant Women &"
                        },
                        {
                            "count": 11034,
                            "title1": "(0 - 2 Years)",
                            "iconImg": "../images/NewDashboard/home_visit_child_img.png",
                            "title": "Children"
                        }
                    ],
                    "district_id": 540
                },
                {
                    "data": [
                        {
                            "count": 3525,
                            "title1": "Lactating Mother",
                            "iconImg": "../images/NewDashboard/home_visit_preg_women_img.png",
                            "title": "Pregnant Women &"
                        },
                        {
                            "count": 7125,
                            "title1": "(0 - 2 Years)",
                            "iconImg": "../images/NewDashboard/home_visit_child_img.png",
                            "title": "Children"
                        }
                    ],
                    "district_id": 541
                },
                {
                    "data": [
                        {
                            "count": 7590,
                            "title1": "Lactating Mother",
                            "iconImg": "../images/NewDashboard/home_visit_preg_women_img.png",
                            "title": "Pregnant Women &"
                        },
                        {
                            "count": 14469,
                            "title1": "(0 - 2 Years)",
                            "iconImg": "../images/NewDashboard/home_visit_child_img.png",
                            "title": "Children"
                        }
                    ],
                    "district_id": 542
                },
                {
                    "data": [
                        {
                            "count": 8094,
                            "title1": "Lactating Mother",
                            "iconImg": "../images/NewDashboard/home_visit_preg_women_img.png",
                            "title": "Pregnant Women &"
                        },
                        {
                            "count": 15370,
                            "title1": "(0 - 2 Years)",
                            "iconImg": "../images/NewDashboard/home_visit_child_img.png",
                            "title": "Children"
                        }
                    ],
                    "district_id": 543
                },
                {
                    "data": [
                        {
                            "count": 4554,
                            "title1": "Lactating Mother",
                            "iconImg": "../images/NewDashboard/home_visit_preg_women_img.png",
                            "title": "Pregnant Women &"
                        },
                        {
                            "count": 11919,
                            "title1": "(0 - 2 Years)",
                            "iconImg": "../images/NewDashboard/home_visit_child_img.png",
                            "title": "Children"
                        }
                    ],
                    "district_id": 544
                },
                {
                    "data": [
                        {
                            "count": 3773,
                            "title1": "Lactating Mother",
                            "iconImg": "../images/NewDashboard/home_visit_preg_women_img.png",
                            "title": "Pregnant Women &"
                        },
                        {
                            "count": 8932,
                            "title1": "(0 - 2 Years)",
                            "iconImg": "../images/NewDashboard/home_visit_child_img.png",
                            "title": "Children"
                        }
                    ],
                    "district_id": 545
                },
                {
                    "data": [
                        {
                            "count": 4946,
                            "title1": "Lactating Mother",
                            "iconImg": "../images/NewDashboard/home_visit_preg_women_img.png",
                            "title": "Pregnant Women &"
                        },
                        {
                            "count": 10031,
                            "title1": "(0 - 2 Years)",
                            "iconImg": "../images/NewDashboard/home_visit_child_img.png",
                            "title": "Children"
                        }
                    ],
                    "district_id": 546
                },
                {
                    "data": [
                        {
                            "count": 5846,
                            "title1": "Lactating Mother",
                            "iconImg": "../images/NewDashboard/home_visit_preg_women_img.png",
                            "title": "Pregnant Women &"
                        },
                        {
                            "count": 13357,
                            "title1": "(0 - 2 Years)",
                            "iconImg": "../images/NewDashboard/home_visit_child_img.png",
                            "title": "Children"
                        }
                    ],
                    "district_id": 547
                },
                {
                    "data": [
                        {
                            "count": 3288,
                            "title1": "Lactating Mother",
                            "iconImg": "../images/NewDashboard/home_visit_preg_women_img.png",
                            "title": "Pregnant Women &"
                        },
                        {
                            "count": 10031,
                            "title1": "(0 - 2 Years)",
                            "iconImg": "../images/NewDashboard/home_visit_child_img.png",
                            "title": "Children"
                        }
                    ],
                    "district_id": 548
                },
                {
                    "data": [
                        {
                            "count": 7149,
                            "title1": "Lactating Mother",
                            "iconImg": "../images/NewDashboard/home_visit_preg_women_img.png",
                            "title": "Pregnant Women &"
                        },
                        {
                            "count": 19839,
                            "title1": "(0 - 2 Years)",
                            "iconImg": "../images/NewDashboard/home_visit_child_img.png",
                            "title": "Children"
                        }
                    ],
                    "district_id": 549
                },
                {
                    "data": [
                        {
                            "count": 4808,
                            "title1": "Lactating Mother",
                            "iconImg": "../images/NewDashboard/home_visit_preg_women_img.png",
                            "title": "Pregnant Women &"
                        },
                        {
                            "count": 11469,
                            "title1": "(0 - 2 Years)",
                            "iconImg": "../images/NewDashboard/home_visit_child_img.png",
                            "title": "Children"
                        }
                    ],
                    "district_id": 550
                },
                {
                    "data": [
                        {
                            "count": 3601,
                            "title1": "Lactating Mother",
                            "iconImg": "../images/NewDashboard/home_visit_preg_women_img.png",
                            "title": "Pregnant Women &"
                        },
                        {
                            "count": 5400,
                            "title1": "(0 - 2 Years)",
                            "iconImg": "../images/NewDashboard/home_visit_child_img.png",
                            "title": "Children"
                        }
                    ],
                    "district_id": 551
                },
                {
                    "data": [
                        {
                            "count": 7537,
                            "title1": "Lactating Mother",
                            "iconImg": "../images/NewDashboard/home_visit_preg_women_img.png",
                            "title": "Pregnant Women &"
                        },
                        {
                            "count": 18660,
                            "title1": "(0 - 2 Years)",
                            "iconImg": "../images/NewDashboard/home_visit_child_img.png",
                            "title": "Children"
                        }
                    ],
                    "district_id": 552
                },
                {
                    "data": [
                        {
                            "count": 2764,
                            "title1": "Lactating Mother",
                            "iconImg": "../images/NewDashboard/home_visit_preg_women_img.png",
                            "title": "Pregnant Women &"
                        },
                        {
                            "count": 7173,
                            "title1": "(0 - 2 Years)",
                            "iconImg": "../images/NewDashboard/home_visit_child_img.png",
                            "title": "Children"
                        }
                    ],
                    "district_id": 553
                },
                {
                    "data": [
                        {
                            "count": 4016,
                            "title1": "Lactating Mother",
                            "iconImg": "../images/NewDashboard/home_visit_preg_women_img.png",
                            "title": "Pregnant Women &"
                        },
                        {
                            "count": 12468,
                            "title1": "(0 - 2 Years)",
                            "iconImg": "../images/NewDashboard/home_visit_child_img.png",
                            "title": "Children"
                        }
                    ],
                    "district_id": 554
                },
                {
                    "data": [
                        {
                            "count": 4568,
                            "title1": "Lactating Mother",
                            "iconImg": "../images/NewDashboard/home_visit_preg_women_img.png",
                            "title": "Pregnant Women &"
                        },
                        {
                            "count": 13956,
                            "title1": "(0 - 2 Years)",
                            "iconImg": "../images/NewDashboard/home_visit_child_img.png",
                            "title": "Children"
                        }
                    ],
                    "district_id": 555
                },
                {
                    "data": [
                        {
                            "count": 606,
                            "title1": "Lactating Mother",
                            "iconImg": "../images/NewDashboard/home_visit_preg_women_img.png",
                            "title": "Pregnant Women &"
                        },
                        {
                            "count": 1520,
                            "title1": "(0 - 2 Years)",
                            "iconImg": "../images/NewDashboard/home_visit_child_img.png",
                            "title": "Children"
                        }
                    ],
                    "district_id": 556
                },
                {
                    "data": [
                        {
                            "count": 4297,
                            "title1": "Lactating Mother",
                            "iconImg": "../images/NewDashboard/home_visit_preg_women_img.png",
                            "title": "Pregnant Women &"
                        },
                        {
                            "count": 11596,
                            "title1": "(0 - 2 Years)",
                            "iconImg": "../images/NewDashboard/home_visit_child_img.png",
                            "title": "Children"
                        }
                    ],
                    "district_id": 557
                },
                {
                    "data": [
                        {
                            "count": 5769,
                            "title1": "Lactating Mother",
                            "iconImg": "../images/NewDashboard/home_visit_preg_women_img.png",
                            "title": "Pregnant Women &"
                        },
                        {
                            "count": 18602,
                            "title1": "(0 - 2 Years)",
                            "iconImg": "../images/NewDashboard/home_visit_child_img.png",
                            "title": "Children"
                        }
                    ],
                    "district_id": 558
                },
                {
                    "data": [
                        {
                            "count": 2011,
                            "title1": "Lactating Mother",
                            "iconImg": "../images/NewDashboard/home_visit_preg_women_img.png",
                            "title": "Pregnant Women &"
                        },
                        {
                            "count": 5862,
                            "title1": "(0 - 2 Years)",
                            "iconImg": "../images/NewDashboard/home_visit_child_img.png",
                            "title": "Children"
                        }
                    ],
                    "district_id": 559
                },
                {
                    "data": [
                        {
                            "count": 2529,
                            "title1": "Lactating Mother",
                            "iconImg": "../images/NewDashboard/home_visit_preg_women_img.png",
                            "title": "Pregnant Women &"
                        },
                        {
                            "count": 6039,
                            "title1": "(0 - 2 Years)",
                            "iconImg": "../images/NewDashboard/home_visit_child_img.png",
                            "title": "Children"
                        }
                    ],
                    "district_id": 560
                },
                {
                    "data": [
                        {
                            "count": 2570,
                            "title1": "Lactating Mother",
                            "iconImg": "../images/NewDashboard/home_visit_preg_women_img.png",
                            "title": "Pregnant Women &"
                        },
                        {
                            "count": 5963,
                            "title1": "(0 - 2 Years)",
                            "iconImg": "../images/NewDashboard/home_visit_child_img.png",
                            "title": "Children"
                        }
                    ],
                    "district_id": 602
                },
                {
                    "data": [
                        {
                            "count": 3513,
                            "title1": "Lactating Mother",
                            "iconImg": "../images/NewDashboard/home_visit_preg_women_img.png",
                            "title": "Pregnant Women &"
                        },
                        {
                            "count": 9491,
                            "title1": "(0 - 2 Years)",
                            "iconImg": "../images/NewDashboard/home_visit_child_img.png",
                            "title": "Children"
                        }
                    ],
                    "district_id": 603
                },
                {
                    "data": [
                        {
                            "count": 6642,
                            "title1": "Lactating Mother",
                            "iconImg": "../images/NewDashboard/home_visit_preg_women_img.png",
                            "title": "Pregnant Women &"
                        },
                        {
                            "count": 14365,
                            "title1": "(0 - 2 Years)",
                            "iconImg": "../images/NewDashboard/home_visit_child_img.png",
                            "title": "Children"
                        }
                    ],
                    "district_id": 605
                },
                {
                    "data": [
                        {
                            "count": 2886,
                            "title1": "Lactating Mother",
                            "iconImg": "../images/NewDashboard/home_visit_preg_women_img.png",
                            "title": "Pregnant Women &"
                        },
                        {
                            "count": 5775,
                            "title1": "(0 - 2 Years)",
                            "iconImg": "../images/NewDashboard/home_visit_child_img.png",
                            "title": "Children"
                        }
                    ],
                    "district_id": 607
                },
                {
                    "data": [
                        {
                            "count": 141331,
                            "title1": "Lactating Mother",
                            "iconImg": "../images/NewDashboard/home_visit_preg_women_img.png",
                            "title": "Pregnant Women &"
                        },
                        {
                            "count": 352999,
                            "title1": "(0 - 2 Years)",
                            "iconImg": "../images/NewDashboard/home_visit_child_img.png",
                            "title": "Children"
                        }
                    ],
                    "district_id": 0
                }
            ],
            "id": 32
        }
    ]
}